easygTTS/__init__.py
easygTTS/gtts.py
easygTTS-1.0.dist-info/LICENCE.txt
easygTTS-1.0.dist-info/METADATA
easygTTS-1.0.dist-info/WHEEL
easygTTS-1.0.dist-info/top_level.txt
easygTTS-1.0.dist-info/RECORD
