Metadata-Version: 2.1
Name: easygTTS
Version: 1.0
Summary: Easy async interface to easy-gtts-api
Home-page: https://github.com/gnome-py/py-easygTTS
Author: Gnome-py
Author-email: gnome6669.py@gmail.com
License: MIT
Download-URL: https://github.com/Gnome-py/py-easygTTS/archive/v1.0.tar.gz
Keywords: async,TTS,gtts,text to speech
Platform: UNKNOWN
Classifier: Development Status :: 5 - Production/Stable
Classifier: Intended Audience :: Developers
Classifier: Topic :: Software Development :: Build Tools
Classifier: License :: OSI Approved :: MIT License
Classifier: Programming Language :: Python :: 3
Classifier: Programming Language :: Python :: 3.6
Classifier: Programming Language :: Python :: 3.7
Classifier: Programming Language :: Python :: 3.8
Classifier: Programming Language :: Python :: 3.9
Requires-Dist: aiohttp
